{
  "status": "success",
  "data": [
    {
      "obj_id": "ZTF23abbskff",
      "ra": null,
      "dec": null,
      "filter": "ztfr",
      "mjd": 60170.48238429986,
      "snr": null,
      "instrument_id": 1,
      "instrument_name": "ZTF",
      "ra_unc": null,
      "dec_unc": null,
      "origin": "None",
      "id": 489544354,
      "altdata": null,
      "created_at": "2023-09-08T12:33:01.027425",
      "groups": [
        {
          "id": 3,
          "name": "kowalski-bot",
          "nickname": null,
          "single_user_group": true
        }
      ],
      "mag": null,
      "magerr": null,
      "magsys": "ab",
      "limiting_mag": 20.256799697875977
    },
    {
      "obj_id": "ZTF23abbskff",
      "ra": null,
      "dec": null,
      "filter": "ztfr",
      "mjd": 60173.458194400184,
      "snr": null,
      "instrument_id": 1,
      "instrument_name": "ZTF",
      "ra_unc": null,
      "dec_unc": null,
      "origin": "None",
      "id": 489544355,
      "altdata": null,
      "created_at": "2023-09-08T12:33:01.027490",
      "groups": [
        {
          "id": 3,
          "name": "kowalski-bot",
          "nickname": null,
          "single_user_group": true
        }
      ],
      "mag": null,
      "magerr": null,
      "magsys": "ab",
      "limiting_mag": 20.23819923400879
    },
    {
      "obj_id": "ZTF23abbskff",
      "ra": null,
      "dec": null,
      "filter": "ztfg",
      "mjd": 60178.45733800018,
      "snr": null,
      "instrument_id": 1,
      "instrument_name": "ZTF",
      "ra_unc": null,
      "dec_unc": null,
      "origin": "None",
      "id": 489544356,
      "altdata": null,
      "created_at": "2023-09-08T12:33:01.027510",
      "groups": [
        {
          "id": 3,
          "name": "kowalski-bot",
          "nickname": null,
          "single_user_group": true
        }
      ],
      "mag": null,
      "magerr": null,
      "magsys": "ab",
      "limiting_mag": 20.460500717163086
    },
    {
      "obj_id": "ZTF23abbskff",
      "ra": null,
      "dec": null,
      "filter": "ztfg",
      "mjd": 60182.41865740018,
      "snr": null,
      "instrument_id": 1,
      "instrument_name": "ZTF",
      "ra_unc": null,
      "dec_unc": null,
      "origin": "None",
      "id": 489544357,
      "altdata": null,
      "created_at": "2023-09-08T12:33:01.027526",
      "groups": [
        {
          "id": 3,
          "name": "kowalski-bot",
          "nickname": null,
          "single_user_group": true
        }
      ],
      "mag": null,
      "magerr": null,
      "magsys": "ab",
      "limiting_mag": 20.05150032043457
    },
    {
      "obj_id": "ZTF23abbskff",
      "ra": null,
      "dec": null,
      "filter": "ztfr",
      "mjd": 60182.463634300046,
      "snr": null,
      "instrument_id": 1,
      "instrument_name": "ZTF",
      "ra_unc": null,
      "dec_unc": null,
      "origin": "None",
      "id": 489544358,
      "altdata": null,
      "created_at": "2023-09-08T12:33:01.027541",
      "groups": [
        {
          "id": 3,
          "name": "kowalski-bot",
          "nickname": null,
          "single_user_group": true
        }
      ],
      "mag": null,
      "magerr": null,
      "magsys": "ab",
      "limiting_mag": 20.29400062561035
    },
    {
      "obj_id": "ZTF23abbskff",
      "ra": null,
      "dec": null,
      "filter": "ztfg",
      "mjd": 60184.44247689983,
      "snr": null,
      "instrument_id": 1,
      "instrument_name": "ZTF",
      "ra_unc": null,
      "dec_unc": null,
      "origin": "None",
      "id": 489544359,
      "altdata": null,
      "created_at": "2023-09-08T12:33:01.027556",
      "groups": [
        {
          "id": 3,
          "name": "kowalski-bot",
          "nickname": null,
          "single_user_group": true
        }
      ],
      "mag": null,
      "magerr": null,
      "magsys": "ab",
      "limiting_mag": 20.24090003967285
    },
    {
      "obj_id": "ZTF23abbskff",
      "ra": null,
      "dec": null,
      "filter": "ztfr",
      "mjd": 60184.48967589997,
      "snr": null,
      "instrument_id": 1,
      "instrument_name": "ZTF",
      "ra_unc": null,
      "dec_unc": null,
      "origin": "None",
      "id": 489544360,
      "altdata": null,
      "created_at": "2023-09-08T12:33:01.027571",
      "groups": [
        {
          "id": 3,
          "name": "kowalski-bot",
          "nickname": null,
          "single_user_group": true
        }
      ],
      "mag": null,
      "magerr": null,
      "magsys": "ab",
      "limiting_mag": 20.31559944152832
    },
    {
      "obj_id": "ZTF23abbskff",
      "ra": null,
      "dec": null,
      "filter": "ztfr",
      "mjd": 60187.41189809982,
      "snr": null,
      "instrument_id": 1,
      "instrument_name": "ZTF",
      "ra_unc": null,
      "dec_unc": null,
      "origin": "None",
      "id": 489545971,
      "altdata": null,
      "created_at": "2023-09-08T12:41:11.940687",
      "groups": [
        {
          "id": 3,
          "name": "kowalski-bot",
          "nickname": null,
          "single_user_group": true
        }
      ],
      "mag": null,
      "magerr": null,
      "magsys": "ab",
      "limiting_mag": 19.052200317382812
    },
    {
      "obj_id": "ZTF23abbskff",
      "ra": null,
      "dec": null,
      "filter": "ztfr",
      "mjd": 60187.45604170021,
      "snr": null,
      "instrument_id": 1,
      "instrument_name": "ZTF",
      "ra_unc": null,
      "dec_unc": null,
      "origin": "None",
      "id": 489544361,
      "altdata": null,
      "created_at": "2023-09-08T12:33:01.027584",
      "groups": [
        {
          "id": 3,
          "name": "kowalski-bot",
          "nickname": null,
          "single_user_group": true
        }
      ],
      "mag": null,
      "magerr": null,
      "magsys": "ab",
      "limiting_mag": 19.336599349975586
    },
    {
      "obj_id": "ZTF23abbskff",
      "ra": null,
      "dec": null,
      "filter": "ztfg",
      "mjd": 60187.479861100204,
      "snr": null,
      "instrument_id": 1,
      "instrument_name": "ZTF",
      "ra_unc": null,
      "dec_unc": null,
      "origin": "None",
      "id": 489544362,
      "altdata": null,
      "created_at": "2023-09-08T12:33:01.027598",
      "groups": [
        {
          "id": 3,
          "name": "kowalski-bot",
          "nickname": null,
          "single_user_group": true
        }
      ],
      "mag": null,
      "magerr": null,
      "magsys": "ab",
      "limiting_mag": 19.03529930114746
    },
    {
      "obj_id": "ZTF23abbskff",
      "ra": null,
      "dec": null,
      "filter": "ztfg",
      "mjd": 60192.38351849979,
      "snr": null,
      "instrument_id": 1,
      "instrument_name": "ZTF",
      "ra_unc": null,
      "dec_unc": null,
      "origin": "None",
      "id": 489544363,
      "altdata": null,
      "created_at": "2023-09-08T12:33:01.027612",
      "groups": [
        {
          "id": 3,
          "name": "kowalski-bot",
          "nickname": null,
          "single_user_group": true
        }
      ],
      "mag": null,
      "magerr": null,
      "magsys": "ab",
      "limiting_mag": 19.467199325561523
    },
    {
      "obj_id": "ZTF23abbskff",
      "ra": null,
      "dec": null,
      "filter": "ztfr",
      "mjd": 60192.44841440022,
      "snr": null,
      "instrument_id": 1,
      "instrument_name": "ZTF",
      "ra_unc": null,
      "dec_unc": null,
      "origin": "None",
      "id": 489544364,
      "altdata": null,
      "created_at": "2023-09-08T12:33:01.027627",
      "groups": [
        {
          "id": 3,
          "name": "kowalski-bot",
          "nickname": null,
          "single_user_group": true
        }
      ],
      "mag": null,
      "magerr": null,
      "magsys": "ab",
      "limiting_mag": 19.883399963378906
    },
    {
      "obj_id": "ZTF23abbskff",
      "ra": null,
      "dec": null,
      "filter": "ztfg",
      "mjd": 60195.408738399856,
      "snr": null,
      "instrument_id": 1,
      "instrument_name": "ZTF",
      "ra_unc": null,
      "dec_unc": null,
      "origin": "None",
      "id": 489544365,
      "altdata": null,
      "created_at": "2023-09-08T12:33:01.027640",
      "groups": [
        {
          "id": 3,
          "name": "kowalski-bot",
          "nickname": null,
          "single_user_group": true
        }
      ],
      "mag": null,
      "magerr": null,
      "magsys": "ab",
      "limiting_mag": 19.80699920654297
    },
    {
      "obj_id": "ZTF23abbskff",
      "ra": 53.3346382,
      "dec": -15.502312,
      "filter": "ztfr",
      "mjd": 60195.470821800176,
      "snr": 8.241758081104356,
      "instrument_id": 1,
      "instrument_name": "ZTF",
      "ra_unc": null,
      "dec_unc": null,
      "origin": "None",
      "id": 498682501,
      "altdata": null,
      "created_at": "2023-09-28T09:39:53.975751",
      "groups": [
        {
          "id": 3,
          "name": "kowalski-bot",
          "nickname": null,
          "single_user_group": true
        }
      ],
      "mag": 19.443100253551144,
      "magerr": 0.13173599541187284,
      "magsys": "ab",
      "limiting_mag": 19.985724899223715
    },
    {
      "obj_id": "ZTF23abbskff",
      "ra": 53.3346382,
      "dec": -15.502312,
      "filter": "ztfr",
      "mjd": 60195.470821800176,
      "snr": 8.24172918124768,
      "instrument_id": 1,
      "instrument_name": "ZTF",
      "ra_unc": null,
      "dec_unc": null,
      "origin": "None",
      "id": 489545972,
      "altdata": null,
      "created_at": "2023-09-08T12:41:11.940788",
      "groups": [
        {
          "id": 3,
          "name": "kowalski-bot",
          "nickname": null,
          "single_user_group": true
        }
      ],
      "mag": 19.443056405453333,
      "magerr": 0.13173645734786987,
      "magsys": "ab",
      "limiting_mag": 19.985677243967842
    },
    {
      "obj_id": "ZTF23abbskff",
      "ra": 53.3345866,
      "dec": -15.5023574,
      "filter": "ztfr",
      "mjd": 60195.4802778,
      "snr": 8.393071901345019,
      "instrument_id": 1,
      "instrument_name": "ZTF",
      "ra_unc": null,
      "dec_unc": null,
      "origin": "None",
      "id": 491059846,
      "altdata": null,
      "created_at": "2023-09-11T11:14:16.714287",
      "groups": [
        {
          "id": 3,
          "name": "kowalski-bot",
          "nickname": null,
          "single_user_group": true
        }
      ],
      "mag": 19.50869964741366,
      "magerr": 0.12936100363731382,
      "magsys": "ab",
      "limiting_mag": 20.07107699562637
    },
    {
      "obj_id": "ZTF23abbskff",
      "ra": 53.3345866,
      "dec": -15.5023574,
      "filter": "ztfr",
      "mjd": 60195.4802778,
      "snr": 8.393041930580388,
      "instrument_id": 1,
      "instrument_name": "ZTF",
      "ra_unc": null,
      "dec_unc": null,
      "origin": "None",
      "id": 489544366,
      "altdata": null,
      "created_at": "2023-09-08T12:33:01.027653",
      "groups": [
        {
          "id": 3,
          "name": "kowalski-bot",
          "nickname": null,
          "single_user_group": true
        }
      ],
      "mag": 19.50869964741366,
      "magerr": 0.12936146557331085,
      "magsys": "ab",
      "limiting_mag": 20.071073118571256
    },
    {
      "obj_id": "ZTF23abbskff",
      "ra": 53.3346002,
      "dec": -15.5023802,
      "filter": "ztfr",
      "mjd": 60198.4389698999,
      "snr": 13.680461932417451,
      "instrument_id": 1,
      "instrument_name": "ZTF",
      "ra_unc": null,
      "dec_unc": null,
      "origin": "None",
      "id": 491921635,
      "altdata": null,
      "created_at": "2023-09-14T10:52:53.047323",
      "groups": [
        {
          "id": 3,
          "name": "kowalski-bot",
          "nickname": null,
          "single_user_group": true
        }
      ],
      "mag": 18.899700178344037,
      "magerr": 0.07936400175094604,
      "magsys": "ab",
      "limiting_mag": 19.992527072388377
    },
    {
      "obj_id": "ZTF23abbskff",
      "ra": 53.3346002,
      "dec": -15.5023802,
      "filter": "ztfr",
      "mjd": 60198.4389698999,
      "snr": 13.680499177290757,
      "instrument_id": 1,
      "instrument_name": "ZTF",
      "ra_unc": null,
      "dec_unc": null,
      "origin": "None",
      "id": 491059847,
      "altdata": null,
      "created_at": "2023-09-11T11:14:16.714345",
      "groups": [
        {
          "id": 3,
          "name": "kowalski-bot",
          "nickname": null,
          "single_user_group": true
        }
      ],
      "mag": 18.899690654979675,
      "magerr": 0.07936378568410873,
      "magsys": "ab",
      "limiting_mag": 19.992520504922183
    },
    {
      "obj_id": "ZTF23abbskff",
      "ra": 53.3346356,
      "dec": -15.5024172,
      "filter": "ztfr",
      "mjd": 60201.43741900008,
      "snr": 13.388070129484479,
      "instrument_id": 1,
      "instrument_name": "ZTF",
      "ra_unc": null,
      "dec_unc": null,
      "origin": "None",
      "id": 491921636,
      "altdata": null,
      "created_at": "2023-09-14T10:52:53.047407",
      "groups": [
        {
          "id": 3,
          "name": "kowalski-bot",
          "nickname": null,
          "single_user_group": true
        }
      ],
      "mag": 18.97562253911592,
      "magerr": 0.0810972899198532,
      "magsys": "ab",
      "limiting_mag": 20.044992474816254
    },
    {
      "obj_id": "ZTF23abbskff",
      "ra": 53.3346356,
      "dec": -15.5024172,
      "filter": "ztfr",
      "mjd": 60201.43741900008,
      "snr": 13.388118099285549,
      "instrument_id": 1,
      "instrument_name": "ZTF",
      "ra_unc": null,
      "dec_unc": null,
      "origin": "None",
      "id": 491958059,
      "altdata": null,
      "created_at": "2023-09-14T12:23:24.093269",
      "groups": [
        {
          "id": 3,
          "name": "kowalski-bot",
          "nickname": null,
          "single_user_group": true
        }
      ],
      "mag": 18.975599537488044,
      "magerr": 0.08109699934720992,
      "magsys": "ab",
      "limiting_mag": 20.044973363402274
    },
    {
      "obj_id": "ZTF23abbskff",
      "ra": 53.3346903,
      "dec": -15.5023983,
      "filter": "ztfg",
      "mjd": 60201.4827083,
      "snr": 5.466866974333436,
      "instrument_id": 1,
      "instrument_name": "ZTF",
      "ra_unc": null,
      "dec_unc": null,
      "origin": "None",
      "id": 493087109,
      "altdata": null,
      "created_at": "2023-09-16T12:31:23.221251",
      "groups": [
        {
          "id": 3,
          "name": "kowalski-bot",
          "nickname": null,
          "single_user_group": true
        }
      ],
      "mag": 20.264400716717283,
      "magerr": 0.19860300421714783,
      "magsys": "ab",
      "limiting_mag": 20.361321971630538
    },
    {
      "obj_id": "ZTF23abbskff",
      "ra": 53.3346903,
      "dec": -15.5023983,
      "filter": "ztfg",
      "mjd": 60201.4827083,
      "snr": 5.466866974333436,
      "instrument_id": 1,
      "instrument_name": "ZTF",
      "ra_unc": null,
      "dec_unc": null,
      "origin": "None",
      "id": 491958060,
      "altdata": null,
      "created_at": "2023-09-14T12:23:24.093345",
      "groups": [
        {
          "id": 3,
          "name": "kowalski-bot",
          "nickname": null,
          "single_user_group": true
        }
      ],
      "mag": 20.264364626529026,
      "magerr": 0.19860300421714783,
      "magsys": "ab",
      "limiting_mag": 20.36128588144228
    },
    {
      "obj_id": "ZTF23abbskff",
      "ra": null,
      "dec": null,
      "filter": "ztfg",
      "mjd": 60203.39836810017,
      "snr": null,
      "instrument_id": 1,
      "instrument_name": "ZTF",
      "ra_unc": null,
      "dec_unc": null,
      "origin": "None",
      "id": 493087110,
      "altdata": null,
      "created_at": "2023-09-16T12:31:23.221328",
      "groups": [
        {
          "id": 3,
          "name": "kowalski-bot",
          "nickname": null,
          "single_user_group": true
        }
      ],
      "mag": null,
      "magerr": null,
      "magsys": "ab",
      "limiting_mag": 20.552200317382812
    },
    {
      "obj_id": "ZTF23abbskff",
      "ra": 53.3346148,
      "dec": -15.5023816,
      "filter": "ztfr",
      "mjd": 60203.48126159981,
      "snr": 12.936673890544979,
      "instrument_id": 1,
      "instrument_name": "ZTF",
      "ra_unc": null,
      "dec_unc": null,
      "origin": "None",
      "id": 494212648,
      "altdata": null,
      "created_at": "2023-09-18T11:31:17.962553",
      "groups": [
        {
          "id": 3,
          "name": "kowalski-bot",
          "nickname": null,
          "single_user_group": true
        }
      ],
      "mag": 18.948500002991675,
      "magerr": 0.08392699807882309,
      "magsys": "ab",
      "limiting_mag": 19.9806315684811
    },
    {
      "obj_id": "ZTF23abbskff",
      "ra": 53.3346148,
      "dec": -15.5023816,
      "filter": "ztfr",
      "mjd": 60203.48126159981,
      "snr": 12.936692265727334,
      "instrument_id": 1,
      "instrument_name": "ZTF",
      "ra_unc": null,
      "dec_unc": null,
      "origin": "None",
      "id": 493087111,
      "altdata": null,
      "created_at": "2023-09-16T12:31:23.221361",
      "groups": [
        {
          "id": 3,
          "name": "kowalski-bot",
          "nickname": null,
          "single_user_group": true
        }
      ],
      "mag": 18.94849610513264,
      "magerr": 0.08392687886953354,
      "magsys": "ab",
      "limiting_mag": 19.980629212794863
    },
    {
      "obj_id": "ZTF23abbskff",
      "ra": 53.334646,
      "dec": -15.5023469,
      "filter": "ztfr",
      "mjd": 60205.418587999884,
      "snr": 11.700912378600126,
      "instrument_id": 1,
      "instrument_name": "ZTF",
      "ra_unc": null,
      "dec_unc": null,
      "origin": "None",
      "id": 494212649,
      "altdata": null,
      "created_at": "2023-09-18T11:31:17.962613",
      "groups": [
        {
          "id": 3,
          "name": "kowalski-bot",
          "nickname": null,
          "single_user_group": true
        }
      ],
      "mag": 18.990205982623195,
      "magerr": 0.09279073029756545,
      "magsys": "ab",
      "limiting_mag": 19.913330289726026
    },
    {
      "obj_id": "ZTF23abbskff",
      "ra": 53.334646,
      "dec": -15.5023469,
      "filter": "ztfr",
      "mjd": 60205.418587999884,
      "snr": 11.700878556038493,
      "instrument_id": 1,
      "instrument_name": "ZTF",
      "ra_unc": null,
      "dec_unc": null,
      "origin": "None",
      "id": 495468844,
      "altdata": null,
      "created_at": "2023-09-20T13:14:40.196664",
      "groups": [
        {
          "id": 3,
          "name": "kowalski-bot",
          "nickname": null,
          "single_user_group": true
        }
      ],
      "mag": 18.990200311929332,
      "magerr": 0.09279099851846694,
      "magsys": "ab",
      "limiting_mag": 19.913321480607436
    },
    {
      "obj_id": "ZTF23abbskff",
      "ra": null,
      "dec": null,
      "filter": "ztfg",
      "mjd": 60205.477789400145,
      "snr": null,
      "instrument_id": 1,
      "instrument_name": "ZTF",
      "ra_unc": null,
      "dec_unc": null,
      "origin": "None",
      "id": 495468845,
      "altdata": null,
      "created_at": "2023-09-20T13:14:40.196724",
      "groups": [
        {
          "id": 3,
          "name": "kowalski-bot",
          "nickname": null,
          "single_user_group": true
        }
      ],
      "mag": null,
      "magerr": null,
      "magsys": "ab",
      "limiting_mag": 20.697500228881836
    },
    {
      "obj_id": "ZTF23abbskff",
      "ra": null,
      "dec": null,
      "filter": "ztfg",
      "mjd": 60207.455844900105,
      "snr": null,
      "instrument_id": 1,
      "instrument_name": "ZTF",
      "ra_unc": null,
      "dec_unc": null,
      "origin": "None",
      "id": 495468846,
      "altdata": null,
      "created_at": "2023-09-20T13:14:40.196759",
      "groups": [
        {
          "id": 3,
          "name": "kowalski-bot",
          "nickname": null,
          "single_user_group": true
        }
      ],
      "mag": null,
      "magerr": null,
      "magsys": "ab",
      "limiting_mag": 20.840200424194336
    },
    {
      "obj_id": "ZTF23abbskff",
      "ra": 53.3346238,
      "dec": -15.5023456,
      "filter": "ztfr",
      "mjd": 60207.461458299775,
      "snr": 10.528743740103286,
      "instrument_id": 1,
      "instrument_name": "ZTF",
      "ra_unc": null,
      "dec_unc": null,
      "origin": "None",
      "id": 495468847,
      "altdata": null,
      "created_at": "2023-09-20T13:14:40.196775",
      "groups": [
        {
          "id": 3,
          "name": "kowalski-bot",
          "nickname": null,
          "single_user_group": true
        }
      ],
      "mag": 18.876535476391197,
      "magerr": 0.10312115401029585,
      "magsys": "ab",
      "limiting_mag": 19.685051854272558
    },
    {
      "obj_id": "ZTF23abbskff",
      "ra": 53.3346238,
      "dec": -15.5023456,
      "filter": "ztfr",
      "mjd": 60207.461458299775,
      "snr": 10.52875971502953,
      "instrument_id": 1,
      "instrument_name": "ZTF",
      "ra_unc": null,
      "dec_unc": null,
      "origin": "None",
      "id": 497288840,
      "altdata": null,
      "created_at": "2023-09-25T12:45:05.475115",
      "groups": [
        {
          "id": 3,
          "name": "kowalski-bot",
          "nickname": null,
          "single_user_group": true
        }
      ],
      "mag": 18.876499646648647,
      "magerr": 0.10312099754810335,
      "magsys": "ab",
      "limiting_mag": 19.685017671881585
    },
    {
      "obj_id": "ZTF23abbskff",
      "ra": null,
      "dec": null,
      "filter": "ztfg",
      "mjd": 60212.41737269983,
      "snr": null,
      "instrument_id": 1,
      "instrument_name": "ZTF",
      "ra_unc": null,
      "dec_unc": null,
      "origin": "None",
      "id": 497288841,
      "altdata": null,
      "created_at": "2023-09-25T12:45:05.475173",
      "groups": [
        {
          "id": 3,
          "name": "kowalski-bot",
          "nickname": null,
          "single_user_group": true
        }
      ],
      "mag": null,
      "magerr": null,
      "magsys": "ab",
      "limiting_mag": 20.523000717163086
    },
    {
      "obj_id": "ZTF23abbskff",
      "ra": 53.334652,
      "dec": -15.5023706,
      "filter": "ztfr",
      "mjd": 60212.4400578998,
      "snr": 12.809383912120307,
      "instrument_id": 1,
      "instrument_name": "ZTF",
      "ra_unc": null,
      "dec_unc": null,
      "origin": "None",
      "id": 498391076,
      "altdata": null,
      "created_at": "2023-09-27T13:08:12.559224",
      "groups": [
        {
          "id": 3,
          "name": "kowalski-bot",
          "nickname": null,
          "single_user_group": true
        }
      ],
      "mag": 18.90600039213178,
      "magerr": 0.08476100116968155,
      "magsys": "ab",
      "limiting_mag": 19.927395986683724
    },
    {
      "obj_id": "ZTF23abbskff",
      "ra": 53.334652,
      "dec": -15.5023706,
      "filter": "ztfr",
      "mjd": 60212.4400578998,
      "snr": 12.809325362559735,
      "instrument_id": 1,
      "instrument_name": "ZTF",
      "ra_unc": null,
      "dec_unc": null,
      "origin": "None",
      "id": 497288842,
      "altdata": null,
      "created_at": "2023-09-25T12:45:05.475192",
      "groups": [
        {
          "id": 3,
          "name": "kowalski-bot",
          "nickname": null,
          "single_user_group": true
        }
      ],
      "mag": 18.905975654048216,
      "magerr": 0.08476138859987259,
      "magsys": "ab",
      "limiting_mag": 19.927366285869446
    },
    {
      "obj_id": "ZTF23abbskff",
      "ra": null,
      "dec": null,
      "filter": "ztfg",
      "mjd": 60213.37543979986,
      "snr": null,
      "instrument_id": 1,
      "instrument_name": "ZTF",
      "ra_unc": null,
      "dec_unc": null,
      "origin": "None",
      "id": 498682502,
      "altdata": null,
      "created_at": "2023-09-28T09:39:53.975808",
      "groups": [
        {
          "id": 3,
          "name": "kowalski-bot",
          "nickname": null,
          "single_user_group": true
        }
      ],
      "mag": null,
      "magerr": null,
      "magsys": "ab",
      "limiting_mag": 19.405399322509766
    },
    {
      "obj_id": "ZTF23abbskff",
      "ra": null,
      "dec": null,
      "filter": "ztfg",
      "mjd": 60214.43108800007,
      "snr": null,
      "instrument_id": 1,
      "instrument_name": "ZTF",
      "ra_unc": null,
      "dec_unc": null,
      "origin": "None",
      "id": 498391077,
      "altdata": null,
      "created_at": "2023-09-27T13:08:12.559291",
      "groups": [
        {
          "id": 3,
          "name": "kowalski-bot",
          "nickname": null,
          "single_user_group": true
        }
      ],
      "mag": null,
      "magerr": null,
      "magsys": "ab",
      "limiting_mag": 19.479799270629883
    },
    {
      "obj_id": "ZTF23abbskff",
      "ra": 53.3346376,
      "dec": -15.5023709,
      "filter": "ztfr",
      "mjd": 60214.48120369995,
      "snr": 10.553525757110958,
      "instrument_id": 1,
      "instrument_name": "ZTF",
      "ra_unc": null,
      "dec_unc": null,
      "origin": "None",
      "id": 498682500,
      "altdata": null,
      "created_at": "2023-09-28T09:39:53.798208",
      "groups": [
        {
          "id": 3,
          "name": "kowalski-bot",
          "nickname": null,
          "single_user_group": true
        }
      ],
      "mag": 19.187500271312437,
      "magerr": 0.10287900269031525,
      "magsys": "ab",
      "limiting_mag": 19.99856919653589
    },
    {
      "obj_id": "ZTF23abbskff",
      "ra": 53.3346376,
      "dec": -15.5023709,
      "filter": "ztfr",
      "mjd": 60214.48120369995,
      "snr": 10.553481428194557,
      "instrument_id": 1,
      "instrument_name": "ZTF",
      "ra_unc": null,
      "dec_unc": null,
      "origin": "None",
      "id": 498391078,
      "altdata": null,
      "created_at": "2023-09-27T13:08:12.559310",
      "groups": [
        {
          "id": 3,
          "name": "kowalski-bot",
          "nickname": null,
          "single_user_group": true
        }
      ],
      "mag": 19.187450832265235,
      "magerr": 0.10287943482398987,
      "magsys": "ab",
      "limiting_mag": 19.998515196964398
    },
    {
      "obj_id": "ZTF23abbskff",
      "ra": 53.3345858,
      "dec": -15.5024214,
      "filter": "ztfr",
      "mjd": 60215.34225689992,
      "snr": 5.6757758939925065,
      "instrument_id": 1,
      "instrument_name": "ZTF",
      "ra_unc": null,
      "dec_unc": null,
      "origin": "None",
      "id": 502336613,
      "altdata": null,
      "created_at": "2023-10-07T12:27:36.679406",
      "groups": [
        {
          "id": 3,
          "name": "kowalski-bot",
          "nickname": null,
          "single_user_group": true
        }
      ],
      "mag": 19.24430120090535,
      "magerr": 0.19129300117492676,
      "magsys": "ab",
      "limiting_mag": 19.38193928796447
    },
    {
      "obj_id": "ZTF23abbskff",
      "ra": 53.3345858,
      "dec": -15.5024214,
      "filter": "ztfr",
      "mjd": 60215.34225689992,
      "snr": 5.675763956609677,
      "instrument_id": 1,
      "instrument_name": "ZTF",
      "ra_unc": null,
      "dec_unc": null,
      "origin": "None",
      "id": 498682503,
      "altdata": null,
      "created_at": "2023-09-28T09:39:53.975828",
      "groups": [
        {
          "id": 3,
          "name": "kowalski-bot",
          "nickname": null,
          "single_user_group": true
        }
      ],
      "mag": 19.24427435725902,
      "magerr": 0.19129340350627896,
      "magsys": "ab",
      "limiting_mag": 19.38191016077795
    },
    {
      "obj_id": "ZTF23abbskff",
      "ra": null,
      "dec": null,
      "filter": "ztfg",
      "mjd": 60216.41837960016,
      "snr": null,
      "instrument_id": 1,
      "instrument_name": "ZTF",
      "ra_unc": null,
      "dec_unc": null,
      "origin": "None",
      "id": 502336614,
      "altdata": null,
      "created_at": "2023-10-07T12:27:36.679490",
      "groups": [
        {
          "id": 3,
          "name": "kowalski-bot",
          "nickname": null,
          "single_user_group": true
        }
      ],
      "mag": null,
      "magerr": null,
      "magsys": "ab",
      "limiting_mag": 18.68939971923828
    },
    {
      "obj_id": "ZTF23abbskff",
      "ra": null,
      "dec": null,
      "filter": "ztfg",
      "mjd": 60216.47623840021,
      "snr": null,
      "instrument_id": 1,
      "instrument_name": "ZTF",
      "ra_unc": null,
      "dec_unc": null,
      "origin": "None",
      "id": 502336602,
      "altdata": null,
      "created_at": "2023-10-07T12:27:36.408416",
      "groups": [
        {
          "id": 3,
          "name": "kowalski-bot",
          "nickname": null,
          "single_user_group": true
        }
      ],
      "mag": null,
      "magerr": null,
      "magsys": "ab",
      "limiting_mag": 18.98390007019043
    },
    {
      "obj_id": "ZTF23abbskff",
      "ra": null,
      "dec": null,
      "filter": "ztfr",
      "mjd": 60216.48202549992,
      "snr": null,
      "instrument_id": 1,
      "instrument_name": "ZTF",
      "ra_unc": null,
      "dec_unc": null,
      "origin": "None",
      "id": 502336603,
      "altdata": null,
      "created_at": "2023-10-07T12:27:36.408477",
      "groups": [
        {
          "id": 3,
          "name": "kowalski-bot",
          "nickname": null,
          "single_user_group": true
        }
      ],
      "mag": null,
      "magerr": null,
      "magsys": "ab",
      "limiting_mag": 19.265199661254883
    },
    {
      "obj_id": "ZTF23abbskff",
      "ra": null,
      "dec": null,
      "filter": "ztfr",
      "mjd": 60217.34724539984,
      "snr": null,
      "instrument_id": 1,
      "instrument_name": "ZTF",
      "ra_unc": null,
      "dec_unc": null,
      "origin": "None",
      "id": 502336615,
      "altdata": null,
      "created_at": "2023-10-07T12:27:36.679522",
      "groups": [
        {
          "id": 3,
          "name": "kowalski-bot",
          "nickname": null,
          "single_user_group": true
        }
      ],
      "mag": null,
      "magerr": null,
      "magsys": "ab",
      "limiting_mag": 18.684799194335938
    },
    {
      "obj_id": "ZTF23abbskff",
      "ra": null,
      "dec": null,
      "filter": "ztfg",
      "mjd": 60220.449213000014,
      "snr": null,
      "instrument_id": 1,
      "instrument_name": "ZTF",
      "ra_unc": null,
      "dec_unc": null,
      "origin": "None",
      "id": 502336616,
      "altdata": null,
      "created_at": "2023-10-07T12:27:36.679548",
      "groups": [
        {
          "id": 3,
          "name": "kowalski-bot",
          "nickname": null,
          "single_user_group": true
        }
      ],
      "mag": null,
      "magerr": null,
      "magsys": "ab",
      "limiting_mag": 19.122699737548828
    },
    {
      "obj_id": "ZTF23abbskff",
      "ra": null,
      "dec": null,
      "filter": "ztfg",
      "mjd": 60221.40341439983,
      "snr": null,
      "instrument_id": 1,
      "instrument_name": "ZTF",
      "ra_unc": null,
      "dec_unc": null,
      "origin": "None",
      "id": 502336604,
      "altdata": null,
      "created_at": "2023-10-07T12:27:36.408495",
      "groups": [
        {
          "id": 3,
          "name": "kowalski-bot",
          "nickname": null,
          "single_user_group": true
        }
      ],
      "mag": null,
      "magerr": null,
      "magsys": "ab",
      "limiting_mag": 18.981599807739258
    },
    {
      "obj_id": "ZTF23abbskff",
      "ra": null,
      "dec": null,
      "filter": "ztfr",
      "mjd": 60222.368553199805,
      "snr": null,
      "instrument_id": 1,
      "instrument_name": "ZTF",
      "ra_unc": null,
      "dec_unc": null,
      "origin": "None",
      "id": 502336617,
      "altdata": null,
      "created_at": "2023-10-07T12:27:36.679571",
      "groups": [
        {
          "id": 3,
          "name": "kowalski-bot",
          "nickname": null,
          "single_user_group": true
        }
      ],
      "mag": null,
      "magerr": null,
      "magsys": "ab",
      "limiting_mag": 19.558799743652344
    },
    {
      "obj_id": "ZTF23abbskff",
      "ra": null,
      "dec": null,
      "filter": "ztfg",
      "mjd": 60223.400902799796,
      "snr": null,
      "instrument_id": 1,
      "instrument_name": "ZTF",
      "ra_unc": null,
      "dec_unc": null,
      "origin": "None",
      "id": 502336605,
      "altdata": null,
      "created_at": "2023-10-07T12:27:36.408511",
      "groups": [
        {
          "id": 3,
          "name": "kowalski-bot",
          "nickname": null,
          "single_user_group": true
        }
      ],
      "mag": null,
      "magerr": null,
      "magsys": "ab",
      "limiting_mag": 19.853599548339844
    },
    {
      "obj_id": "ZTF23abbskff",
      "ra": null,
      "dec": null,
      "filter": "ztfr",
      "mjd": 60223.47613430023,
      "snr": null,
      "instrument_id": 1,
      "instrument_name": "ZTF",
      "ra_unc": null,
      "dec_unc": null,
      "origin": "None",
      "id": 502336606,
      "altdata": null,
      "created_at": "2023-10-07T12:27:36.408525",
      "groups": [
        {
          "id": 3,
          "name": "kowalski-bot",
          "nickname": null,
          "single_user_group": true
        }
      ],
      "mag": null,
      "magerr": null,
      "magsys": "ab",
      "limiting_mag": 19.78730010986328
    },
    {
      "obj_id": "ZTF23abbskff",
      "ra": null,
      "dec": null,
      "filter": "ztfr",
      "mjd": 60224.4142593001,
      "snr": null,
      "instrument_id": 1,
      "instrument_name": "ZTF",
      "ra_unc": null,
      "dec_unc": null,
      "origin": "None",
      "id": 508079710,
      "altdata": null,
      "created_at": "2023-10-21T11:12:12.367114",
      "groups": [
        {
          "id": 3,
          "name": "kowalski-bot",
          "nickname": null,
          "single_user_group": true
        }
      ],
      "mag": null,
      "magerr": null,
      "magsys": "ab",
      "limiting_mag": 20.06329917907715
    },
    {
      "obj_id": "ZTF23abbskff",
      "ra": null,
      "dec": null,
      "filter": "ztfr",
      "mjd": 60225.443437499925,
      "snr": null,
      "instrument_id": 1,
      "instrument_name": "ZTF",
      "ra_unc": null,
      "dec_unc": null,
      "origin": "None",
      "id": 508079700,
      "altdata": null,
      "created_at": "2023-10-21T11:12:12.208933",
      "groups": [
        {
          "id": 3,
          "name": "kowalski-bot",
          "nickname": null,
          "single_user_group": true
        }
      ],
      "mag": null,
      "magerr": null,
      "magsys": "ab",
      "limiting_mag": 20.256799697875977
    },
    {
      "obj_id": "ZTF23abbskff",
      "ra": null,
      "dec": null,
      "filter": "ztfg",
      "mjd": 60228.394236099906,
      "snr": null,
      "instrument_id": 1,
      "instrument_name": "ZTF",
      "ra_unc": null,
      "dec_unc": null,
      "origin": "None",
      "id": 508079701,
      "altdata": null,
      "created_at": "2023-10-21T11:12:12.208990",
      "groups": [
        {
          "id": 3,
          "name": "kowalski-bot",
          "nickname": null,
          "single_user_group": true
        }
      ],
      "mag": null,
      "magerr": null,
      "magsys": "ab",
      "limiting_mag": 20.36370086669922
    },
    {
      "obj_id": "ZTF23abbskff",
      "ra": null,
      "dec": null,
      "filter": "ztfr",
      "mjd": 60228.43755789986,
      "snr": null,
      "instrument_id": 1,
      "instrument_name": "ZTF",
      "ra_unc": null,
      "dec_unc": null,
      "origin": "None",
      "id": 508079702,
      "altdata": null,
      "created_at": "2023-10-21T11:12:12.209008",
      "groups": [
        {
          "id": 3,
          "name": "kowalski-bot",
          "nickname": null,
          "single_user_group": true
        }
      ],
      "mag": null,
      "magerr": null,
      "magsys": "ab",
      "limiting_mag": 20.234500885009766
    },
    {
      "obj_id": "ZTF23abbskff",
      "ra": null,
      "dec": null,
      "filter": "ztfg",
      "mjd": 60230.42824070016,
      "snr": null,
      "instrument_id": 1,
      "instrument_name": "ZTF",
      "ra_unc": null,
      "dec_unc": null,
      "origin": "None",
      "id": 508079711,
      "altdata": null,
      "created_at": "2023-10-21T11:12:12.367172",
      "groups": [
        {
          "id": 3,
          "name": "kowalski-bot",
          "nickname": null,
          "single_user_group": true
        }
      ],
      "mag": null,
      "magerr": null,
      "magsys": "ab",
      "limiting_mag": 20.04319953918457
    },
    {
      "obj_id": "ZTF23abbskff",
      "ra": null,
      "dec": null,
      "filter": "ztfr",
      "mjd": 60231.39800930023,
      "snr": null,
      "instrument_id": 1,
      "instrument_name": "ZTF",
      "ra_unc": null,
      "dec_unc": null,
      "origin": "None",
      "id": 508079703,
      "altdata": null,
      "created_at": "2023-10-21T11:12:12.209022",
      "groups": [
        {
          "id": 3,
          "name": "kowalski-bot",
          "nickname": null,
          "single_user_group": true
        }
      ],
      "mag": null,
      "magerr": null,
      "magsys": "ab",
      "limiting_mag": 20.0935001373291
    },
    {
      "obj_id": "ZTF23abbskff",
      "ra": null,
      "dec": null,
      "filter": "ztfg",
      "mjd": 60233.376817100216,
      "snr": null,
      "instrument_id": 1,
      "instrument_name": "ZTF",
      "ra_unc": null,
      "dec_unc": null,
      "origin": "None",
      "id": 508079704,
      "altdata": null,
      "created_at": "2023-10-21T11:12:12.209036",
      "groups": [
        {
          "id": 3,
          "name": "kowalski-bot",
          "nickname": null,
          "single_user_group": true
        }
      ],
      "mag": null,
      "magerr": null,
      "magsys": "ab",
      "limiting_mag": 20.335899353027344
    },
    {
      "obj_id": "ZTF23abbskff",
      "ra": null,
      "dec": null,
      "filter": "ztfr",
      "mjd": 60233.44362269994,
      "snr": null,
      "instrument_id": 1,
      "instrument_name": "ZTF",
      "ra_unc": null,
      "dec_unc": null,
      "origin": "None",
      "id": 508079705,
      "altdata": null,
      "created_at": "2023-10-21T11:12:12.209050",
      "groups": [
        {
          "id": 3,
          "name": "kowalski-bot",
          "nickname": null,
          "single_user_group": true
        }
      ],
      "mag": null,
      "magerr": null,
      "magsys": "ab",
      "limiting_mag": 20.215900421142578
    },
    {
      "obj_id": "ZTF23abbskff",
      "ra": null,
      "dec": null,
      "filter": "ztfg",
      "mjd": 60235.37640050007,
      "snr": null,
      "instrument_id": 1,
      "instrument_name": "ZTF",
      "ra_unc": null,
      "dec_unc": null,
      "origin": "None",
      "id": 508079706,
      "altdata": null,
      "created_at": "2023-10-21T11:12:12.209063",
      "groups": [
        {
          "id": 3,
          "name": "kowalski-bot",
          "nickname": null,
          "single_user_group": true
        }
      ],
      "mag": null,
      "magerr": null,
      "magsys": "ab",
      "limiting_mag": 20.517900466918945
    },
    {
      "obj_id": "ZTF23abbskff",
      "ra": null,
      "dec": null,
      "filter": "ztfr",
      "mjd": 60235.4248147998,
      "snr": null,
      "instrument_id": 1,
      "instrument_name": "ZTF",
      "ra_unc": null,
      "dec_unc": null,
      "origin": "None",
      "id": 508079707,
      "altdata": null,
      "created_at": "2023-10-21T11:12:12.209076",
      "groups": [
        {
          "id": 3,
          "name": "kowalski-bot",
          "nickname": null,
          "single_user_group": true
        }
      ],
      "mag": null,
      "magerr": null,
      "magsys": "ab",
      "limiting_mag": 20.239500045776367
    },
    {
      "obj_id": "ZTF23abbskff",
      "ra": null,
      "dec": null,
      "filter": "ztfr",
      "mjd": 60236.370312499814,
      "snr": null,
      "instrument_id": 1,
      "instrument_name": "ZTF",
      "ra_unc": null,
      "dec_unc": null,
      "origin": "None",
      "id": 508079712,
      "altdata": null,
      "created_at": "2023-10-21T11:12:12.367191",
      "groups": [
        {
          "id": 3,
          "name": "kowalski-bot",
          "nickname": null,
          "single_user_group": true
        }
      ],
      "mag": null,
      "magerr": null,
      "magsys": "ab",
      "limiting_mag": 20.20949935913086
    },
    {
      "obj_id": "ZTF23abbskff",
      "ra": null,
      "dec": null,
      "filter": "ztfr",
      "mjd": 60237.34067129996,
      "snr": null,
      "instrument_id": 1,
      "instrument_name": "ZTF",
      "ra_unc": null,
      "dec_unc": null,
      "origin": "None",
      "id": 508079713,
      "altdata": null,
      "created_at": "2023-10-21T11:12:12.367211",
      "groups": [
        {
          "id": 3,
          "name": "kowalski-bot",
          "nickname": null,
          "single_user_group": true
        }
      ],
      "mag": null,
      "magerr": null,
      "magsys": "ab",
      "limiting_mag": 20.101299285888672
    },
    {
      "obj_id": "ZTF23abbskff",
      "ra": null,
      "dec": null,
      "filter": "ztfr",
      "mjd": 60237.35505789984,
      "snr": null,
      "instrument_id": 1,
      "instrument_name": "ZTF",
      "ra_unc": null,
      "dec_unc": null,
      "origin": "None",
      "id": 508079708,
      "altdata": null,
      "created_at": "2023-10-21T11:12:12.209088",
      "groups": [
        {
          "id": 3,
          "name": "kowalski-bot",
          "nickname": null,
          "single_user_group": true
        }
      ],
      "mag": null,
      "magerr": null,
      "magsys": "ab",
      "limiting_mag": 20.31100082397461
    },
    {
      "obj_id": "ZTF23abbskff",
      "ra": null,
      "dec": null,
      "filter": "ztfg",
      "mjd": 60237.433854199946,
      "snr": null,
      "instrument_id": 1,
      "instrument_name": "ZTF",
      "ra_unc": null,
      "dec_unc": null,
      "origin": "None",
      "id": 508079709,
      "altdata": null,
      "created_at": "2023-10-21T11:12:12.209102",
      "groups": [
        {
          "id": 3,
          "name": "kowalski-bot",
          "nickname": null,
          "single_user_group": true
        }
      ],
      "mag": null,
      "magerr": null,
      "magsys": "ab",
      "limiting_mag": 20.2987003326416
    },
    {
      "obj_id": "ZTF23abbskff",
      "ra": null,
      "dec": null,
      "filter": "ztfr",
      "mjd": 60238.388414400164,
      "snr": null,
      "instrument_id": 1,
      "instrument_name": "ZTF",
      "ra_unc": null,
      "dec_unc": null,
      "origin": "None",
      "id": 508079714,
      "altdata": null,
      "created_at": "2023-10-21T11:12:12.367225",
      "groups": [
        {
          "id": 3,
          "name": "kowalski-bot",
          "nickname": null,
          "single_user_group": true
        }
      ],
      "mag": null,
      "magerr": null,
      "magsys": "ab",
      "limiting_mag": 20.380199432373047
    }
  ],
  "version": "1.4.0+fritz.143bd07"
}